geminiplayground/__init__.py
geminiplayground/catching.py
geminiplayground/cli.py
geminiplayground/core/__init__.py
geminiplayground/core/gemini_client.py
geminiplayground/core/gemini_playground.py
geminiplayground/parts/__init__.py
geminiplayground/parts/multimodal_part.py
geminiplayground/parts/multimodal_part_factory.py
geminiplayground/parts/audio_part/__init__.py
geminiplayground/parts/audio_part/audio_part.py
geminiplayground/parts/git_repo/__init__.py
geminiplayground/parts/git_repo/git_repo_part.py
geminiplayground/parts/image_part/__init__.py
geminiplayground/parts/image_part/image_part.py
geminiplayground/parts/pdf_part/__init__.py
geminiplayground/parts/pdf_part/pdf_part.py
geminiplayground/parts/video_part/__init__.py
geminiplayground/parts/video_part/video_part.py
geminiplayground/rag/__init__.py
geminiplayground/rag/agentic_tool_use.py
geminiplayground/rag/lotr_rag.py
geminiplayground/rag/rag.py
geminiplayground/rag/routing_rag.py
geminiplayground/rag/summarization_loader.py
geminiplayground/utils/__init__.py
geminiplayground/utils/cacheable.py
geminiplayground/utils/file_utils.py
geminiplayground/utils/git_remote_progress.py
geminiplayground/utils/git_utils.py
geminiplayground/utils/image_utils.py
geminiplayground/utils/lib_utils.py
geminiplayground/utils/pdf_utils.py
geminiplayground/utils/prompts.py
geminiplayground/utils/singleton.py
geminiplayground/utils/video_utils.py
geminiplayground/web/__init__.py
geminiplayground/web/api.py
geminiplayground/web/app.py
geminiplayground/web/utils.py
geminiplayground/web/web.py
geminiplayground/web/db/__init__.py
geminiplayground/web/db/config.py
geminiplayground/web/db/models.py
geminiplayground/web/db/registry.py
geminiplayground/web/db/session_manager.py
geminiplayground/web/files/thumbnail_audio.png
geminiplayground/web/files/thumbnail_github.png
geminiplayground/web/static/404.html
geminiplayground/web/static/coding.png
geminiplayground/web/static/favicon.ico
geminiplayground/web/static/files.html
geminiplayground-1.0.2.dist-info/METADATA
geminiplayground-1.0.2.dist-info/WHEEL
geminiplayground-1.0.2.dist-info/entry_points.txt
geminiplayground-1.0.2.dist-info/licenses/LICENSE
geminiplayground-1.0.2.dist-info/RECORD
