Metadata-Version: 2.4
Name: geminiplayground
Version: 1.0.2
Summary: Add your description here
License-File: LICENSE
Requires-Python: >=3.10
Requires-Dist: aiosqlite>=0.21.0
Requires-Dist: alive-progress>=3.2.0
Requires-Dist: arrow>=1.3.0
Requires-Dist: diskcache>=5.6.3
Requires-Dist: fastapi[standard]>=0.115.11
Requires-Dist: gitingest>=0.1.4
Requires-Dist: gitpython>=3.1.44
Requires-Dist: google-genai>=1.7.0
Requires-Dist: greenlet>=3.1.1
Requires-Dist: langchain-core>=0.3.47
Requires-Dist: langchain-google-genai>=2.1.1
Requires-Dist: langchain>=0.3.21
Requires-Dist: opencv-python>=4.11.0.86
Requires-Dist: pillow>=11.1.0
Requires-Dist: pydantic-settings>=2.8.1
Requires-Dist: pygithub>=2.6.1
Requires-Dist: pymupdf>=1.25.4
Requires-Dist: rich>=13.9.4
Requires-Dist: tenacity>=9.0.0
Requires-Dist: tqdm>=4.67.1
Requires-Dist: validators>=0.34.0
Requires-Dist: websockets>=15.0.1
Requires-Dist: yaspin>=3.1.0
Provides-Extra: demos
Requires-Dist: langchain-weaviate>=0.0.4; extra == 'demos'
